cellular_automata_class/__init__.py
cellular_automata_class/cell.py
cellular_automata_class/game_of_life.py
cellular_automata_class-0.0.4.dist-info/LICENSE
cellular_automata_class-0.0.4.dist-info/METADATA
cellular_automata_class-0.0.4.dist-info/WHEEL
cellular_automata_class-0.0.4.dist-info/top_level.txt
cellular_automata_class-0.0.4.dist-info/RECORD
