Metadata-Version: 2.1
Name: cellular-automata-class
Version: 0.0.4
Summary: An expandable cell class intended for constructing Cellular Automata
Home-page: https://github.com/ceferisbarov/cellular-automata-class
Author: Jafar Isbarov
Author-email: cefer.isbarov@gmail.com
License: UNKNOWN
Project-URL: Bug Tracker, https://github.com/ceferisbarov/cellular-automata-class/issues
Platform: UNKNOWN
Classifier: Programming Language :: Python :: 3
Classifier: License :: OSI Approved :: MIT License
Classifier: Operating System :: OS Independent
Requires-Python: >=3.6
